pcsuite/__init__.py
pcsuite/agent/__init__.py
pcsuite/agent/runner.py
pcsuite/agent/service.py
pcsuite/cleaners/__init__.py
pcsuite/cleaners/apps_common.py
pcsuite/cleaners/browsers.py
pcsuite/cleaners/delivery_optimization.py
pcsuite/cleaners/dumps_caches.py
pcsuite/cleaners/dumps_thumbs_fonts.py
pcsuite/cleaners/recycle_bin.py
pcsuite/cleaners/updates_leftovers.py
pcsuite/cleaners/windows_temp.py
pcsuite/cli/__init__.py
pcsuite/cli/clean.py
pcsuite/cli/drivers.py
pcsuite/cli/edr.py
pcsuite/cli/main.py
pcsuite/cli/optimize.py
pcsuite/cli/process.py
pcsuite/cli/registry.py
pcsuite/cli/schedule.py
pcsuite/cli/security.py
pcsuite/cli/services.py
pcsuite/cli/startup.py
pcsuite/cli/system.py
pcsuite/cli/tasks.py
pcsuite/cli/ui.py
pcsuite/core/__init__.py
pcsuite/core/audit.py
pcsuite/core/backup.py
pcsuite/core/elevation.py
pcsuite/core/fs.py
pcsuite/core/profiles.py
pcsuite/core/registry.py
pcsuite/core/shell.py
pcsuite/data/exclusions.yml
pcsuite/data/optimize_profiles.yml
pcsuite/data/signatures.yml
pcsuite/data/rules/powershell_encodedcommand.yml
pcsuite/data/rules/response_isolate_demo.yml
pcsuite/data/rules/suspicious_keywords.yml
pcsuite/optimize/__init__.py
pcsuite/optimize/disk_policies.py
pcsuite/optimize/explorer_ux.py
pcsuite/optimize/network_stack.py
pcsuite/optimize/power.py
pcsuite/optimize/ssd_hdd.py
pcsuite/optimize/telemetry.py
pcsuite/optimize/visuals.py
pcsuite/security/__init__.py
pcsuite/security/canary.py
pcsuite/security/defender.py
pcsuite/security/edr.py
pcsuite/security/firewall.py
pcsuite/security/hosts.py
pcsuite/security/logs.py
pcsuite/security/netinfo.py
pcsuite/security/reputation.py
pcsuite/security/rules.py
pcsuite/startup/registry_run.py
pcsuite/startup/risk.py
pcsuite/startup/services.py
pcsuite/startup/startup_folder.py
pcsuite/startup/tasks.py
pcsuite/ui/__init__.py
pcsuite/ui/tui.py
pcsuite/ui/gui/__init__.py
pcsuite/ui/gui/app.py
pcsuite-1.0.7.dist-info/licenses/LICENSE
pcsuite-1.0.7.dist-info/METADATA
pcsuite-1.0.7.dist-info/WHEEL
pcsuite-1.0.7.dist-info/entry_points.txt
pcsuite-1.0.7.dist-info/top_level.txt
pcsuite-1.0.7.dist-info/RECORD
